<annotation>
	<folder>Rafid_data</folder>
	<filename>train_rafid_101.jpg</filename>
	<path>D:\IS\Dataset\COS30018_Assignment\DATA_SET\Rafid_data\train_rafid_101.jpg</path>
	<source>
		<database>Unknown</database>
	</source>
	<size>
		<width>640</width>
		<height>640</height>
		<depth>3</depth>
	</size>
	<segmented>0</segmented>
	<object>
		<name>unorganised</name>
		<pose>Unspecified</pose>
		<truncated>0</truncated>
		<difficult>1</difficult>
		<bndbox>
			<xmin>445</xmin>
			<ymin>202</ymin>
			<xmax>481</xmax>
			<ymax>259</ymax>
		</bndbox>
	</object>
	<object>
		<name>unorganised</name>
		<pose>Unspecified</pose>
		<truncated>0</truncated>
		<difficult>1</difficult>
		<bndbox>
			<xmin>481</xmin>
			<ymin>203</ymin>
			<xmax>519</xmax>
			<ymax>257</ymax>
		</bndbox>
	</object>
	<object>
		<name>unorganised</name>
		<pose>Unspecified</pose>
		<truncated>0</truncated>
		<difficult>1</difficult>
		<bndbox>
			<xmin>246</xmin>
			<ymin>438</ymin>
			<xmax>282</xmax>
			<ymax>485</ymax>
		</bndbox>
	</object>
	<object>
		<name>unorganised</name>
		<pose>Unspecified</pose>
		<truncated>0</truncated>
		<difficult>1</difficult>
		<bndbox>
			<xmin>532</xmin>
			<ymin>129</ymin>
			<xmax>584</xmax>
			<ymax>156</ymax>
		</bndbox>
	</object>
</annotation>
